postbode/__init__.py
postbode/client.py
tests/__init__.py
tests/test_client.py
postbode_python-0.1.3.dist-info/LICENSE
postbode_python-0.1.3.dist-info/METADATA
postbode_python-0.1.3.dist-info/WHEEL
postbode_python-0.1.3.dist-info/top_level.txt
postbode_python-0.1.3.dist-info/RECORD
