Metadata-Version: 2.1
Name: postbode-python
Version: 0.1.3
Summary: Python wrapper for api of http://www.postbode.nu for sending postal mail.
Home-page: https://github.com/Heffie/postbode-python
Author: Jeffrey Hagenstein
Author-email: jdhagenstein@gmail.com
License: UNKNOWN
Platform: UNKNOWN
Classifier: Programming Language :: Python :: 3
Classifier: License :: OSI Approved :: MIT License
Classifier: Operating System :: OS Independent
Requires-Python: >=3.6
Requires-Dist: requests (==2.23.0)
